drf_orjson_renderer2/__init__.py
drf_orjson_renderer2/parsers.py
drf_orjson_renderer2/renderers.py
drf_orjson_renderer2-2.0.0.dist-info/licenses/LICENSE
drf_orjson_renderer2-2.0.0.dist-info/WHEEL
drf_orjson_renderer2-2.0.0.dist-info/METADATA
drf_orjson_renderer2-2.0.0.dist-info/RECORD
