Metadata-Version: 2.4
Name: drf-orjson-renderer2
Version: 2.0.0
Summary: "Django RestFramework JSON Renderer Backed by orjson"
Keywords: drf_orjson_renderer,rest_framework,orjson
Author-email: brianjbuck <brian@thebuckpasser.com>
Maintainer-email: Jonathan Dekhtiar <jonathan@dekhtiar.com>
Requires-Python: >=3.10
Classifier: Intended Audience :: Developers
Classifier: Intended Audience :: Science/Research
Classifier: Intended Audience :: Information Technology
Classifier: Topic :: Software Development :: Build Tools
Classifier: Topic :: Scientific/Engineering
Classifier: Topic :: Software Development :: Libraries
Classifier: Topic :: Utilities
Classifier: License :: OSI Approved :: MIT License
Classifier: Operating System :: OS Independent
Classifier: Programming Language :: Python :: 3
Classifier: Programming Language :: Python :: 3 :: Only
License-File: LICENSE
Requires-Dist: django>=3.2
Requires-Dist: djangorestframework
Requires-Dist: orjson>=3.3.0
Requires-Dist: jsondiff>=2.2,<2.3 ; extra == "test"
Requires-Dist: numpy>=2.0.0 ; extra == "test"
Requires-Dist: pytest>=8.0.0,<9.0.0 ; extra == "test"
Requires-Dist: pytest-cov>=5.0.0,<8.0.0 ; extra == "test"
Requires-Dist: pytest-dotenv>=0.5.0,<1.0.0 ; extra == "test"
Requires-Dist: pytest-env>=1.1.3,<2.0.0 ; extra == "test"
Requires-Dist: pytest-runner>=6.0.0,<7.0.0 ; extra == "test"
Requires-Dist: pytest-ordering>=0.6,<1.0.0 ; extra == "test"
Requires-Dist: pytest-xdist>=3.6.0,<3.9.0 ; extra == "test"
Requires-Dist: parameterized>=0.9.0,<0.10 ; extra == "test"
Project-URL: Bug Reports, https://github.com/OpenSpeleo/drf-orjson-renderer2/issues
Project-URL: Homepage, https://pypi.org/project/drf-orjson-renderer2/
Project-URL: Source, https://github.com/OpenSpeleo/drf-orjson-renderer2
Provides-Extra: test
